{
  "project_info": {
    "project_number": "1005982410731",
    "firebase_url": "https://bicentenariolalibertad-91fe3.firebaseio.com",
    "project_id": "bicentenariolalibertad-91fe3",
    "storage_bucket": "bicentenariolalibertad-91fe3.appspot.com"
  },
  "client": [
    {
      "client_info": {
        "mobilesdk_app_id": "1:1005982410731:android:747be35a1cf706b6ef9bae",
        "android_client_info": {
          "package_name": "com.pe.bicentenariolalibertad"
        }
      },
      "oauth_client": [
        {
          "client_id": "1005982410731-8ed7hmepcjovntmtppc246tub8bnbuml.apps.googleusercontent.com",
          "client_type": 3
        }
      ],
      "api_key": [
        {
          "current_key": "AIzaSyCLW7ykFmzoEcyW3cbgvaJYgLjQWpPfz84"
        }
      ],
      "services": {
        "appinvite_service": {
          "other_platform_oauth_client": [
            {
              "client_id": "1005982410731-8ed7hmepcjovntmtppc246tub8bnbuml.apps.googleusercontent.com",
              "client_type": 3
            }
          ]
        }
      }
    }
  ],
  "configuration_version": "1"
}